gecatsim/__init__.py
gecatsim/bowtie/large.txt
gecatsim/bowtie/medium.txt
gecatsim/bowtie/small.txt
gecatsim/cfg/Phantom_Default.cfg
gecatsim/cfg/Physics_Default.cfg
gecatsim/cfg/Protocol_Default.cfg
gecatsim/cfg/Recon_Default.cfg
gecatsim/cfg/Scanner_Default.cfg
gecatsim/clib_build/BuildLinux64
gecatsim/clib_build/BuildWin64.bat
gecatsim/clib_build/MakeMacOS
gecatsim/clib_build/MakeVariables_1
gecatsim/clib_build/MakeVariables_2
gecatsim/clib_build/MakeVariables_3
gecatsim/clib_build/MakeWindows64
gecatsim/clib_build/Makefile
gecatsim/clib_build/readme.md
gecatsim/clib_build/src/BaseObject.cpp
gecatsim/clib_build/src/BaseObject.h
gecatsim/clib_build/src/ClipPlane.cpp
gecatsim/clib_build/src/ClipPlane.h
gecatsim/clib_build/src/CrossSection.cpp
gecatsim/clib_build/src/CrossSection.hpp
gecatsim/clib_build/src/CrossSectionHandler.cpp
gecatsim/clib_build/src/CrossSectionHandler.hpp
gecatsim/clib_build/src/Cube.cpp
gecatsim/clib_build/src/Cube.h
gecatsim/clib_build/src/Cylinder.cpp
gecatsim/clib_build/src/Cylinder.h
gecatsim/clib_build/src/DD2Back.c
gecatsim/clib_build/src/DD2ParProj.c
gecatsim/clib_build/src/DD2Proj.c
gecatsim/clib_build/src/DD2WBack.c
gecatsim/clib_build/src/DD3.hpp
gecatsim/clib_build/src/DD3Proj.cpp
gecatsim/clib_build/src/DD3Proj_roi_notrans_mm.cpp
gecatsim/clib_build/src/DD3WBack.c
gecatsim/clib_build/src/DD3_roi_notrans_mm.hpp
gecatsim/clib_build/src/Detector.cpp
gecatsim/clib_build/src/Detector.hpp
gecatsim/clib_build/src/Interpolate.cpp
gecatsim/clib_build/src/Intersection.cpp
gecatsim/clib_build/src/Intersection.h
gecatsim/clib_build/src/MatVec.cpp
gecatsim/clib_build/src/MatVec.h
gecatsim/clib_build/src/Objects.cpp
gecatsim/clib_build/src/Objects.hpp
gecatsim/clib_build/src/Phantom.cpp
gecatsim/clib_build/src/Phantom.hpp
gecatsim/clib_build/src/Photon.cpp
gecatsim/clib_build/src/Photon.hpp
gecatsim/clib_build/src/RD3Back.cpp
gecatsim/clib_build/src/RD3Intersections.cpp
gecatsim/clib_build/src/RD3bench.cpp
gecatsim/clib_build/src/Sphere.cpp
gecatsim-1.6.8.dist-info/licenses/LICENSE
gecatsim-1.6.8.dist-info/METADATA
gecatsim-1.6.8.dist-info/WHEEL
gecatsim-1.6.8.dist-info/top_level.txt
gecatsim-1.6.8.dist-info/RECORD
