Metadata-Version: 2.4
Name: gecatsim
Version: 1.6.8
Summary: Simulation toolkit for X-ray based cancer imaging
Home-page: https://github.com/xcist/documentation/wiki
Author: Mingye Wu, Paul FitzGerald, James Jobin, Jiayong Zhang, Nandan Reddy, Anupama Debnath, Brion Sarachan, Bruno De Man
Author-email: Mingye.Wu@gehealthcare.com
License: BSD 3-Clause License
License-File: LICENSE
Requires-Dist: numpy
Requires-Dist: scipy
Requires-Dist: matplotlib
Requires-Dist: tqdm
Dynamic: author
Dynamic: author-email
Dynamic: description
Dynamic: description-content-type
Dynamic: home-page
Dynamic: license
Dynamic: license-file
Dynamic: requires-dist
Dynamic: summary
